LICENSE
README.md
setup.py
parseq_XES_scan/XES_scan_nodes.py
parseq_XES_scan/XES_scan_pipeline.py
parseq_XES_scan/XES_scan_start.py
parseq_XES_scan/XES_scan_transforms.py
parseq_XES_scan/XES_scan_widgets.py
parseq_XES_scan/_XES_scan_start_with_actions.py
parseq_XES_scan/__init__.py
parseq_XES_scan/version.py
parseq_XES_scan.egg-info/PKG-INFO
parseq_XES_scan.egg-info/SOURCES.txt
parseq_XES_scan.egg-info/dependency_links.txt
parseq_XES_scan.egg-info/not-zip-safe
parseq_XES_scan.egg-info/requires.txt
parseq_XES_scan.egg-info/top_level.txt
parseq_XES_scan/data/20230908s.h5
parseq_XES_scan/data/scan-42000_albaem_2d_01.h5
parseq_XES_scan/data/scan-42000_albaem_2d_02.h5
parseq_XES_scan/data/scan-42000_eiger_xes.h5
parseq_XES_scan/data/scan-42000_pcap.h5
parseq_XES_scan/doc/_images/Mo-Kb13.gif
parseq_XES_scan/doc/_images/about.gif
parseq_XES_scan/doc/_images/icon-xes-1D.png
parseq_XES_scan/doc/_images/icon-xes-2D.png
parseq_XES_scan/doc/_images/mickey-rtfm.gif
parseq_XES_scan/doc/_images/parseq-XES.ico
parseq_XES_scan/doc/_images/parseq-XES_big.png
parseq_XES_scan/saved/Mo-Kb13-1-2D theta scan.png
parseq_XES_scan/saved/Mo-Kb13-2-1D energy XES.png
parseq_XES_scan/saved/Mo-Kb13.pspj