Metadata-Version: 2.4
Name: parseq_XES_scan
Version: 2025.11.0
Summary: A pipeline for data processing of XES theta scans
Author: Konstantin Klementiev
Author-email: konstantin.klementiev@gmail.com
License: MIT License
Project-URL: Source, https://github.com/kklmn/ParSeq-XES-scan
Keywords: data-analysis pipeline framework gui synchrotron spectroscopy
Platform: OS Independent
Classifier: Development Status :: 5 - Production/Stable
Classifier: Intended Audience :: Science/Research
Classifier: Natural Language :: English
Classifier: Operating System :: OS Independent
Classifier: Programming Language :: Python
Classifier: License :: OSI Approved :: MIT License
Classifier: Intended Audience :: Science/Research
Classifier: Topic :: Scientific/Engineering
Classifier: Topic :: Software Development
Classifier: Topic :: Software Development :: User Interfaces
License-File: LICENSE
Requires-Dist: numpy>=1.8.0
Requires-Dist: scipy>=0.17.0
Requires-Dist: matplotlib>=2.0.0
Requires-Dist: h5py
Requires-Dist: silx>=1.1.0
Requires-Dist: hdf5plugin
Requires-Dist: scikit-image
Dynamic: author
Dynamic: author-email
Dynamic: classifier
Dynamic: description
Dynamic: description-content-type
Dynamic: keywords
Dynamic: license
Dynamic: license-file
Dynamic: platform
Dynamic: project-url
Dynamic: requires-dist
Dynamic: summary
